SpUD_io/RFA.py
SpUD_io/SpUD_upload.py
SpUD_io/__init__.py
spud_io-1.0.3.dist-info/licenses/LICENSE
spud_io-1.0.3.dist-info/METADATA
spud_io-1.0.3.dist-info/WHEEL
spud_io-1.0.3.dist-info/top_level.txt
spud_io-1.0.3.dist-info/RECORD
